README.md
setup.py
pampro/Bout.py
pampro/Bout_Collection.py
pampro/Channel.py
pampro/Time_Series.py
pampro/__init__.py
pampro/artificial_channels.py
pampro/batch_processing.py
pampro/channel_inference.py
pampro/data_loading.py
pampro/diagnostics.py
pampro/hdf5.py
pampro/pampro_fourier.py
pampro/pampro_utilities.py
pampro/time_utilities.py
pampro/triaxial_calibration.py
pampro.egg-info/PKG-INFO
pampro.egg-info/SOURCES.txt
pampro.egg-info/dependency_links.txt
pampro.egg-info/requires.txt
pampro.egg-info/top_level.txt