Metadata-Version: 1.2
Name: pampro
Version: 0.5.2.1
Summary: physical activity monitor processing
Home-page: https://github.com/MRC-Epid/pampro
Author: Philip Cameron
Author-email: philip.cameron@mrc-epid.cam.ac.uk
Maintainer: Philip Cameron
Maintainer-email: philip.cameron@mrc-epid.cam.ac.uk
License: GNU GPL-3.0
Platform: UNKNOWN
